dd_tools/__init__.py
dd_tools/downloader.py
dd_tools-3.7.dist-info/METADATA
dd_tools-3.7.dist-info/WHEEL
dd_tools-3.7.dist-info/entry_points.txt
dd_tools-3.7.dist-info/top_level.txt
dd_tools-3.7.dist-info/RECORD
